Workbook

Sheet 00_INICIO
B1: TENDENCIAS GASTRONÓMICAS · RESEARCH SEMANA 3 · TBNB
B2: The Bar N' Bar · Gastro Consulting — Breakdown · Architecture · Run · Octubre 2026 · v1.0 (borrador para validación)
B4: Para qué sirve | C4: Base de tendencias del sector (Barcelona, Madrid e internacional) con evidencia de negocios reales. Alimenta la semana 4: cruce con el Hospitality Trends Report e incorporación de preguntas nuevas a la Auditoría Gastronómica (v1.1).
B5: Cómo se lee | C5: Cada fila de FICHAS es una tendencia con las cinco preguntas del encargo: qué está pasando · por qué · qué negocios lo hacen · impacto en operación y rentabilidad · aplicabilidad en España. Se añade su vínculo con las áreas (A01–A10) y coherencias (C1–C3) de la auditoría.
B6: Qué se edita | C6: Solo las celdas con texto azul y fondo verde claro (Aplicabilidad, Impacto, Madurez, Evidencia y la decisión TBNB en PREGUNTAS_v1.1). Prioridad, recuentos y mapa se calculan solos.
B7: Prioridad TBNB | C7: Aplicabilidad (Alta 3 · Media 2 · Baja 1) × Impacto en el negocio del cliente (1–3). Rango 1–9. ≥ 6 = prioritaria para la v1.1 de la auditoría y para el discurso comercial.
B8: Evidencia | C8: A · Dato: cifra de estudio, estadística oficial o barómetro. B · Casos: varios negocios reales lo hacen. C · Señal: indicio cualitativo o dato no verificado. (INT) = el dato es de fuera de España.
B9: Madurez | C9: Emergente: pocos casos, aún no generalizado. Creciente: se extiende con rapidez. Consolidada: ya forma parte del mercado.
B10: Signo en rentabilidad | C10: + mejora el margen si se aplica bien · − presiona el margen · ± depende de la ejecución.
B11: Límites | C11: Research de despacho con fuentes públicas a fecha 8-oct-2026. Los datos de proveedores (Orbisk, Coravin, CoverManager) son afirmaciones comerciales. Verificar en el BOE el ámbito exacto de la Ley 1/2025 y el calendario final de Verifactu antes de usarlos con un cliente.
B13: HOJAS
B14: FICHAS | C14: Una fila por tendencia (29) en las 9 áreas de investigación.
B15: MAPA | C15: Resumen por área: nº de tendencias, aplicabilidad alta, prioridad media y máxima.
B16: PRIORIDAD | C16: Tendencias ordenadas por Prioridad TBNB (se recalcula al cambiar aplicabilidad o impacto).
B17: CASOS | C17: Negocios reales usados como evidencia, con ciudad y tendencia.
B18: PREGUNTAS_v1.1 | C18: Preguntas propuestas para la auditoría, con la decisión de TBNB.
B19: FUENTES | C19: Enlaces utilizados.

Sheet FICHAS
B1: FICHAS DE TENDENCIAS
B2: Editar solo las celdas en azul sobre verde claro. Una fila = una tendencia.
B4: ID | C4: Área de investigación | D4: Tendencia | E4: Qué está pasando | F4: Por qué | G4: Qué negocios lo hacen | H4: Mercado | I4: Dato clave | J4: Impacto en la operación | K4: Impacto en la rentabilidad | L4: Signo rentab. | M4: Aplicabilidad España | N4: Por qué esa aplicabilidad | O4: Madurez | P4: Evidencia | Q4: Impacto en el negocio (1–3) | R4: Puntos aplic. | S4: Prioridad TBNB (1–9) | T4: Áreas auditoría | U4: Coherencia | V4: Pregunta propuesta (v1.1) | W4: Fuentes | X4: Orden (aux.)
B5: T01 | C5: Concepto | D5: Casualización de la alta cocina | E5: Chefs con estrella cierran o complementan el menú degustación con barras y bistrós de ticket medio (≈50 €), cartas amplias de bocados y servicio informal; en Londres, triestrellados abren carta a mediodía. | F5: Cliente más selectivo que busca calidad-precio; el menú largo es caro de producir y de vender; la marca del chef rentabiliza mejor en formatos de más rotación. | G5: Bera (Martín Berasategui, Hotel Monument, BCN) sustituye a Oria (cerrado oct. 2025) · Hélène Darroze at The Connaught (Londres, carta de mediodía <135 $) · The Ninth (Londres) · Cardinal (Edimburgo, 'Menú del Mercado' ≈34 $) | H5: BCN · INT | I5: Bera: ≈50 €/persona con barra central y cócteles de afterwork (Time Out, abr. 2026). | J5: Más cubiertos y rotación; cartas más largas que el menú degustación → sube el ICP medio y el riesgo de huérfanos si no se diseña con bases comunes. | K5: Ticket más bajo compensado con volumen y bebida; el margen depende de controlar complejidad y mermas. | L5: ± | M5: Alta | N5: Ya está ocurriendo en BCN y MAD; replicable en grupos con chef de referencia. | O5: Creciente | P5: B · Casos | Q5: 3 | R5: =IF(M5="Alta",3,IF(M5="Media",2,IF(M5="Baja",1,""))) -> 3 | S5: =IF(OR(R5="",Q5=""),"",R5*Q5) -> 9 | T5: A01 · A02 · A10 | U5: C1 · C2 | V5: A01 · ¿El formato (degustación, carta, barra) encaja con el ticket objetivo y con la frecuencia de visita que busca el concepto? | W5: https://www.timeout.es/barcelona/es/noticias/el-chef-com-mas-estrellas-michelin-de-espana-y-el-tercero-del-mundo-abre-un-restaurante-asequible-en-barcelona-042026 | https://www.que.es/2026/07/26/martin-berasategui-cierra-estrella-michelin-tapas/ | https://www.forbesargentina.com/lifestyle/menus-mas-cortos-precios-accesibles-formula-alta-cocina-busca-nuevos-clientes-n96944 | X5: =IF(S5="",0,S5)-ROW()/1000 -> 8.995
B6: T02 | C6: Concepto | D6: Restaurante monoproducto o de origen | E6: Aperturas construidas alrededor de un solo producto u origen (atún rojo, cocina gallega, producto de mercado) con carta que cambia según disponibilidad. | F6: Diferenciación clara y fácil de comunicar; relato de origen; compras concentradas en pocos proveedores. | G6: El Campero (atún rojo de Barbate, Madrid 2026) · Garelos (cocina gallega, Madrid 2026) · Varra (producto de temporada, Madrid 2026) | H6: MAD | I6: 5 aperturas destacadas en Madrid 2026; 3 de ellas definidas por producto u origen (The Objective, ene. 2026). | J6: Menos ingredientes y más transversales; exige dominio de despiece y aprovechamiento integral del producto. | K6: Food cost alto en producto premium; el margen sale del aprovechamiento (cortes, recortes) y de la negociación con 1–2 proveedores. | L6: ± | M6: Alta | N6: Encaja con la cultura de producto española y con el Test de la frase del método. | O6: Consolidada | P6: B · Casos | Q6: 2 | R6: =IF(M6="Alta",3,IF(M6="Media",2,IF(M6="Baja",1,""))) -> 3 | S6: =IF(OR(R6="",Q6=""),"",R6*Q6) -> 6 | T6: A01 · A03 · A04 · A06 | U6: C1 · C3 | V6: A04 · ¿Existe plan de contingencia si falla el proveedor del producto que define el concepto (precio, temporada, cupo)? | W6: https://theobjective.com/gastronomia/2026-01-09/nuevos-restaurantes-abriran-madrid-2026/ | X6: =IF(S6="",0,S6)-ROW()/1000 -> 5.994
B7: T03 | C7: Concepto | D7: Cartas cortas y raciones flexibles | E7: Menos referencias, medias raciones y tamaños a elegir; la Ley 1/2025 recomienda raciones flexibles como buena práctica. | F7: El cliente pide menos (plato único, sin postre); presión de costes y de personal; prevención del desperdicio. | G7: Restauración francesa racionaliza cartas y procesos (Hospitality ON) · cadenas en EE. UU. y Reino Unido reducen porciones y cartas · 'buenas prácticas' del art. 13 Ley 1/2025 | H7: ESP · INT | I7: 37 % de los españoles elige consumos más pequeños fuera de casa (un solo plato, sin postre) · Barómetro AECOC/40dB, mayo 2026. | J7: Menos mise en place, menos huérfanos, menos partidas saturadas; facilita polivalencia. | K7: Baja el ticket por comensal si no se diseña la escalera de precios (media/entera, suplementos). | L7: ± | M7: Alta | N7: Encaja con la cultura de raciones y medias raciones; apoyo normativo. | O7: Creciente | P7: A · Dato | Q7: 3 | R7: =IF(M7="Alta",3,IF(M7="Media",2,IF(M7="Baja",1,""))) -> 3 | S7: =IF(OR(R7="",Q7=""),"",R7*Q7) -> 9 | T7: A02 · A06 · A10 | U7: C2 · C3 | V7: A02 · ¿La carta ofrece formatos de ración (media/entera) con precio y escandallo propios para cada formato? | W7: https://www.bolsamania.com/noticias/empresas/economia--el-66-de-los-espanoles-sale-a-bares-y-restaurantes-igual-o-mas-que-hace-un-ano-impulsado-por-los-jovenes--22469129.html | https://hospitality-on.com/fr/restauration/vers-une-rationalisation-des-menus-et-des-process-dans-la-restauration | https://www.elespanol.com/sociedad/20260509/espana-cambia-normas-bares-restaurantes-deberan-ofrecer-raciones-pequenas-entregar-sobras-gratis/1003744237215_0.html | X7: =IF(S7="",0,S7)-ROW()/1000 -> 8.993
B8: T04 | C8: Producto | D8: Brasa y fuego vivo como eje de la cocina | E8: La parrilla de carbón o leña pasa de técnica a identidad: cartas de cortes, pescado y verdura a la brasa, también en fast casual. | F8: Sabor diferencial difícil de copiar en casa; relato artesanal; pocas elaboraciones previas. | G8: Aleteo (vinculado a Grupo Rocacho, Madrid 2026) · Honest Greens (fast casual con técnicas de fuego, 41 locales) | H8: MAD · BCN · INT | I8: Honest Greens: 41 restaurantes en 6 ciudades de España y Portugal y expansión a Londres y París (HRC, jun. 2026). | J8: Equipo exclusivo y cuello de botella en el pico; depende de un parrillero cualificado; menos mise en place. | K8: Producto caro y merma de cocción; compensa con precio por percepción de valor y carta corta. | L8: ± | M8: Alta | N8: Tradición de asador en España; ojo a licencias de humos en BCN. | O8: Consolidada | P8: B · Casos | Q8: 2 | R8: =IF(M8="Alta",3,IF(M8="Media",2,IF(M8="Baja",1,""))) -> 3 | S8: =IF(OR(R8="",Q8=""),"",R8*Q8) -> 6 | T8: A03 · A07 · A08 · A10 | U8: C2 | V8: A08 · ¿La capacidad de la parrilla/brasa cubre el % de ventas que pasa por ella en el pico, sin depender de una sola persona? | W8: https://theobjective.com/gastronomia/2026-01-09/nuevos-restaurantes-abriran-madrid-2026/ | https://www.hrc.co.uk/news/hg-announces-second-london-opening-victoria-uk-expansion-gathers-pace | X8: =IF(S8="",0,S8)-ROW()/1000 -> 5.992
B9: T05 | C9: Producto | D9: Proteína visible y verdura protagonista (adiós al sucedáneo) | E9: Caen los sucedáneos cárnicos ultraprocesados y crecen los platos 'altos en proteína' y la cocina vegetal sin imitar carne. | F9: Desconfianza hacia el ultraprocesado; auge de la proteína en dietas y en usuarios de GLP-1; cliente más exigente con lo vegetal. | G9: Chipotle (High Protein Menu, 'GLP-1 friendly') · Subway (Protein Pockets) · cierres de Neat Burger y Vurger Co (Londres) · Eleven Madison Park reintroduce carne (2025) · Virens (Rodrigo de la Calle, BCN, cocina vegetal) | H9: INT · BCN | I9: Ventas de alimentación plant-based en Reino Unido −4,5 % (año a ene. 2025). | J9: Platos vegetales de técnica propia en vez de producto comprado: más elaboraciones, menos dependencia de proveedor industrial. | K9: Lo vegetal tiene food cost bajo si se vende por técnica y no como sustituto barato. | L9: + | M9: Media | N9: El consumo de sucedáneos en España es menor; el gancho 'proteína' llega más por cafeterías y fast casual. | O9: Creciente | P9: A · Dato | Q9: 2 | R9: =IF(M9="Alta",3,IF(M9="Media",2,IF(M9="Baja",1,""))) -> 2 | S9: =IF(OR(R9="",Q9=""),"",R9*Q9) -> 4 | T9: A02 · A03 | U9: C1 | V9: A02 · ¿La oferta vegetal y la de alto contenido proteico responden al cliente objetivo, o son platos de compromiso con baja venta? | W9: https://londontheinside.com/where-have-all-the-vegans-gone/ | https://www.axios.com/2026/01/07/restaurant-menu-high-protein-dunkin-subway-chipotle | X9: =IF(S9="",0,S9)-ROW()/1000 -> 3.991
B10: T06 | C10: Producto | D10: Cocinas internacionales concretas y regionales | E10: Se especializa lo 'internacional': libanesa, coreana o del Egeo en lugar de 'fusión'; y cocinas regionales españolas (gallega) en grandes ciudades. | F10: Público joven viajado y expuesto a redes; búsqueda de autenticidad; diferenciación frente a la oferta genérica. | G10: Obe (libanés, platos para compartir, Madrid 2026) · Garelos (gallego, Madrid 2026) · Pocha, Casa Moon, Hana (coreanos, BCN) · tendencia de cocina del Egeo en Reino Unido | H10: MAD · BCN · INT | I10: Señal cualitativa: aperturas 2026 y Restaurant Trends Report 2026 (Reino Unido). | J10: Despensa específica con ingredientes de importación → riesgo de huérfanos y de rotura de stock. | K10: Proveedores especializados con menos competencia de precio. | L10: − | M10: Media | N10: Fuerte en BCN y MAD; débil en ciudades medianas. | O10: Creciente | P10: C · Señal | Q10: 1 | R10: =IF(M10="Alta",3,IF(M10="Media",2,IF(M10="Baja",1,""))) -> 2 | S10: =IF(OR(R10="",Q10=""),"",R10*Q10) -> 2 | T10: A01 · A04 | U10: C1 | V10: A03 · Si el concepto se presenta como 'auténtico' de un origen, ¿producto, técnica y equipo lo sostienen? | W10: https://theobjective.com/gastronomia/2026-01-09/nuevos-restaurantes-abriran-madrid-2026/ | https://tastymondays.substack.com/p/la-invasion-coreana-llega-a-barcelona | https://www.restaurantonline.co.uk/Article/2026/07/20/11-trends-shaping-and-set-to-shape-the-restaurant-sector-in-2026/ | X10: =IF(S10="",0,S10)-ROW()/1000 -> 1.99
B11: T07 | C11: Cliente | D11: Se come antes y se sale de día (tardeo) | E11: Parte del gasto nocturno se desplaza a la tarde y al mediodía; el tardeo ya es una franja de negocio propia. | F11: Conciliación, envejecimiento de la clientela de ocio, menos alcohol entre jóvenes, salud y horarios de trabajo híbrido. | G11: 800 locales de ocio en Madrid con tardeo (Noche Madrid) · restaurantes de Londres con +11 % de reservas a las 18:00 · 24 % de los restaurantes encuestados por España de Noche hace tardeo cada fin de semana | H11: MAD · ESP · INT | I11: Tardeo = 26,3 % de la facturación semanal de los locales que lo ofrecen; gasto medio 45 € en Madrid (Noche Madrid, ago. 2026). 50 % de los españoles ha pasado gasto de noche a día y 30 % come antes (AECOC, may. 2026). | J11: Nueva franja 17–20 h que rompe la curva clásica de producción: turnos partidos, mise en place para tres servicios. | K11: Más horas de venta sobre el mismo alquiler; necesita oferta propia (picoteo, bebida) para no canibalizar la cena. | L11: + | M11: Alta | N11: Fenómeno nacido en España; muy relevante en MAD, creciente en BCN. | O11: Consolidada | P11: A · Dato | Q11: 3 | R11: =IF(M11="Alta",3,IF(M11="Media",2,IF(M11="Baja",1,""))) -> 3 | S11: =IF(OR(R11="",Q11=""),"",R11*Q11) -> 9 | T11: A01 · A07 | U11: C2 · C3 | V11: A07 · ¿Turnos y mise en place están dimensionados con la curva de ventas por franja horaria real (TPV), incluida la tarde? | W11: https://diario.madrid.es/blog/notas-de-prensa/casi-el-60-de-los-locales-de-ocio-de-madrid-reconoce-que-el-tardeo-ha-incrementado-sus-ingresos/ | https://www.xataka.com/magnet/hace-anos-tardeo-era-perfecto-desconocido-hosteleria-espanola-hoy-mueve-26-negocio | https://www.xataka.com/magnet/contracultura-gen-z-no-huele-a-tabaco-a-copas-sino-a-cafe-cenas-tempranas | https://www.bolsamania.com/noticias/empresas/economia--el-66-de-los-espanoles-sale-a-bares-y-restaurantes-igual-o-mas-que-hace-un-ano-impulsado-por-los-jovenes--22469129.html | X11: =IF(S11="",0,S11)-ROW()/1000 -> 8.989
B12: T08 | C12: Cliente | D12: Cliente selectivo: sale igual, gasta con más cuidado | E12: La frecuencia se mantiene pero el gasto por visita se contiene; se exige relación calidad-precio y experiencias distintas. | F12: Precios de restauración por encima del IPC general; renta disponible presionada; más oferta. | G12: Fenómeno de mercado (no de un negocio concreto). | H12: ESP | I12: 66 % sale igual o más que hace un año, pero 20 % gasta menos y 53 % iría en horas valle por mejor precio (AECOC, may. 2026). IPC restaurantes y alojamiento 4,8 % vs 2,3 % general (INE, feb. 2026). Gasto medio en restauración por persona 1.146 € (−1,6 %, 2024). | J12: Menos margen para errores de ejecución: una mala experiencia pesa más. | K12: Presión sobre ticket medio; subir precio sin subir valor percibido erosiona la frecuencia. | L12: − | M12: Alta | N12: Dato nacional. | O12: Consolidada | P12: A · Dato | Q12: 3 | R12: =IF(M12="Alta",3,IF(M12="Media",2,IF(M12="Baja",1,""))) -> 3 | S12: =IF(OR(R12="",Q12=""),"",R12*Q12) -> 9 | T12: A01 · A02 · A05 | U12: C1 · C3 | V12: A01 · ¿Se ha medido la relación calidad-precio percibida en reseñas (tema 'precio') y su evolución tras la última subida de carta? | W12: https://www.bolsamania.com/noticias/empresas/economia--el-66-de-los-espanoles-sale-a-bares-y-restaurantes-igual-o-mas-que-hace-un-ano-impulsado-por-los-jovenes--22469129.html | https://ine.es/dyngs/Prensa/IPC0226.htm | https://otea.es/wp-content/uploads/2025/12/ANUARIO-HOSTELERIA-2025.pdf | https://www.vinetur.com/amp/2026031297440/un-tercio-de-los-hosteleros-espanoles-planea-abrir-nuevos-locales-en-2026-pese-al-impacto-de-la-inflacion.html | X12: =IF(S12="",0,S12)-ROW()/1000 -> 8.988
B13: T09 | C13: Cliente | D13: El comensal solo y la barra | E13: Crecen las reservas de una persona; la barra se convierte en el espacio para ese cliente y para el formato informal. | F13: Más hogares unipersonales, viajes de trabajo, normalización social de comer solo. | G13: Datos de OpenTable (EE. UU.) · barras centrales en nuevos formatos (Bera, BCN) | H13: INT · BCN | I13: Reservas individuales +23 % en un año; gasto medio 94 $ frente a 60 $ por persona del total (OpenTable, jul. 2026). | J13: Mesas de 2 ocupadas por 1 = pérdida de capacidad; la barra resuelve y añade show cooking. | K13: Ticket individual alto, especialmente en bebida. | L13: + | M13: Media | N13: Dato de EE. UU.; en España, señal en zonas de turismo y negocios. | O13: Emergente | P13: A · Dato (INT) | Q13: 1 | R13: =IF(M13="Alta",3,IF(M13="Media",2,IF(M13="Baja",1,""))) -> 2 | S13: =IF(OR(R13="",Q13=""),"",R13*Q13) -> 2 | T13: A01 · A08 | U13: C1 | V13: A08 · ¿La distribución de sala (barra, mesas de 2) se ajusta al tamaño real de grupo que muestran las reservas? | W13: https://axios.com/2026/07/17/solo-dining-reservations-jump-opentable | X13: =IF(S13="",0,S13)-ROW()/1000 -> 1.987
B14: T10 | C14: Cliente | D14: Salud, GLP-1 y menos cantidad | E14: Usuarios de fármacos GLP-1 y consumidores 'saludables' piden menos cantidad y más proteína; las cadenas adaptan porciones. | F14: Expansión de los fármacos para la pérdida de peso en EE. UU., Reino Unido y Australia; cultura del bienestar. | G14: Chipotle, Subway, Starbucks, Smoothie King (EE. UU.) · LEON (Reino Unido) | H14: INT | I14: Usuarios de GLP-1 gastan un 63 % menos en restaurantes (KPMG, mar. 2025); 35 % de los clientes pidió raciones más pequeñas por salud (Circana). | J14: Más formatos de ración → más SKU en la ficha técnica si no se diseña con gramajes escalables. | K14: Menor gasto en comida; se compensa con bebida sin alcohol premium y precio por formato. | L14: − | M14: Media | N14: Penetración aún menor en España; conviene vigilar. | O14: Emergente | P14: A · Dato (INT) | Q14: 1 | R14: =IF(M14="Alta",3,IF(M14="Media",2,IF(M14="Baja",1,""))) -> 2 | S14: =IF(OR(R14="",Q14=""),"",R14*Q14) -> 2 | T14: A02 · A09 | U14: C1 | V14: A09 · ¿Las fichas técnicas recogen gramaje y coste por cada formato de ración que se vende? | W14: https://qsrmedia.com/research/in-focus/restaurants-shrink-menus-more-households-use-glp-1 | https://www.axios.com/2026/01/07/restaurant-menu-high-protein-dunkin-subway-chipotle | X14: =IF(S14="",0,S14)-ROW()/1000 -> 1.986
B15: T11 | C15: Operaciones | D15: Falta de equipos cualificados → cocinas diseñadas para la plantilla real | E15: La falta de personal formado es el principal desafío declarado; la respuesta es simplificar procesos, estandarizar y formar con fichas. | F15: Rotación, salarios, condiciones; demanda constante de cocineros y ayudantes. | G15: Fenómeno sectorial (barómetro HIP; guía Adecco). | H15: ESP · BCN | I15: 34 % de hosteleros: la falta de equipos preparados es su principal desafío en 2026 (HIP, mar. 2026). Barcelona, entre las zonas con más contratación prevista (+10 % interanual, Adecco). | J15: Cartas con ICP alto se vuelven inejecutables si falta una persona clave. | K15: Horas extra, errores y mermas cuando falta personal; coste de rotación. | L15: − | M15: Alta | N15: Dato nacional y local. | O15: Consolidada | P15: A · Dato | Q15: 3 | R15: =IF(M15="Alta",3,IF(M15="Media",2,IF(M15="Baja",1,""))) -> 3 | S15: =IF(OR(R15="",Q15=""),"",R15*Q15) -> 9 | T15: A07 · A09 · A10 | U15: C2 | V15: A07 · ¿Cuántas horas de formación necesita una nueva incorporación para ejecutar cada partida con las fichas? | W15: https://www.vinetur.com/amp/2026031297440/un-tercio-de-los-hosteleros-espanoles-planea-abrir-nuevos-locales-en-2026-pese-al-impacto-de-la-inflacion.html | https://www.adeccogroup.com/-/media/project/adecco-group/adeccogroup/spain-content/2026-press-releases/2026-03-09-ndp-v-guia-salarial-adecco-hosteleria-turismo-2026.pdf | X15: =IF(S15="",0,S15)-ROW()/1000 -> 8.985
B16: T12 | C16: Operaciones | D16: Producción centralizada (cocina central / obrador) | E16: Grupos y cadenas concentran la producción en una cocina central y los locales regeneran y terminan. | F16: Estandarización, menos metros y menos personal cualificado en cada local, compras a escala. | G16: Cal Blay (3 M€, cocina central de 4.000 m², capacidad de 6 M platos/año, 2026) · 365 Obrador (obrador central en L'Hospitalet para su red de panaderías-cafetería) | H16: BCN | I16: Cal Blay pasa de 2 a 6 millones de platos de capacidad (Diari de Tarragona, jul. 2026). | J16: Mise en place en el local cae drásticamente; aparecen logística, APPCC de regeneración y control de lotes. | K16: Baja coste laboral por local; sube inversión fija; solo compensa a partir de cierto número de locales. | L16: + | M16: Media | N16: Alta para grupos con 3+ locales; baja para el restaurante independiente. | O16: Consolidada | P16: B · Casos | Q16: 2 | R16: =IF(M16="Alta",3,IF(M16="Media",2,IF(M16="Baja",1,""))) -> 2 | S16: =IF(OR(R16="",Q16=""),"",R16*Q16) -> 4 | T16: A07 · A08 · A09 | U16: C2 · C3 | V16: A07 · Si hay varios locales, ¿se ha evaluado qué elaboraciones transversales (T9) podrían centralizarse? | W16: https://www.diaridetarragona.com/contenidos-empresariales/266443/cal-blay-inverteix-3-milions-d-euros-nova-cuina-central-i-magatzem-logistic_amp.html | https://www.alimarket.es/restauracion/noticia/372854/365-obrador-se-estrena-en-manresa | X16: =IF(S16="",0,S16)-ROW()/1000 -> 3.984
... B33: T29 | C33: Nuevos formatos | D33: Regulación urbana de Barcelona: la licencia como activo | E33: El plan de usos de Ciutat Vella limita las nuevas licencias de bares y restaurantes por concentración, anchura de calle y dimensiones, y protege los establecimientos emblemáticos. | F33: Combatir el monocultivo turístico y proteger el comercio local. | G33: Ayuntamiento de Barcelona (plan de usos de Ciutat Vella, 2025) · establecimientos emblemáticos protegidos | H33: BCN | I33: Solo afecta a nuevas licencias; los traspasos con licencia incorporada quedan fuera (Ara, jun. 2025). | J33: Reconvertir el local existente es más viable que abrir otro nuevo en zonas saturadas. | K33: La licencia se revaloriza; los cambios de concepto se hacen dentro del local que ya existe. | L33: ± | M33: Alta | N33: Específico de BCN; muy relevante para clientes de TBNB. | O33: Consolidada | P33: A · Dato | Q33: 2 | R33: =IF(M33="Alta",3,IF(M33="Media",2,IF(M33="Baja",1,""))) -> 3 | S33: =IF(OR(R33="",Q33=""),"",R33*Q33) -> 6 | T33: A01 · A08 | U33: C1 · C2 | V33: A08 · ¿El rediseño propuesto es compatible con la licencia y la actividad autorizada del local (humos, aforo, categoría)? | W33: https://es.ara.cat/sociedad/barcelona/ultimo-barcelona-combatir-monocultivo-turistico-comercio-ciutat-vella_1_5410794.html | X33: =IF(S33="",0,S33)-ROW()/1000 -> 5.967

Sheet MAPA
B1: MAPA POR ÁREA DE INVESTIGACIÓN
B2: Automatizado – no tocar.
B4: Área | C4: Nº tendencias | D4: Aplicabilidad alta | E4: Prioritarias (≥ 6) | F4: Prioridad media | G4: Prioridad máx.
B5: Concepto | C5: =COUNTIF(FICHAS!$C$5:$C$33,B5) -> 3 | D5: =COUNTIFS(FICHAS!$C$5:$C$33,B5,FICHAS!$M$5:$M$33,"Alta") -> 3 | E5: =COUNTIFS(FICHAS!$C$5:$C$33,B5,FICHAS!$S$5:$S$33,">=6") -> 3 | F5: =IFERROR(AVERAGEIF(FICHAS!$C$5:$C$33,B5,FICHAS!$S$5:$S$33),"") -> 8 | G5: =IFERROR(SUMPRODUCT(MAX((FICHAS!$C$5:$C$33=B5)*FICHAS!$S$5:$S$33)),"") -> 9
B6: Producto | C6: =COUNTIF(FICHAS!$C$5:$C$33,B6) -> 3 | D6: =COUNTIFS(FICHAS!$C$5:$C$33,B6,FICHAS!$M$5:$M$33,"Alta") -> 1 | E6: =COUNTIFS(FICHAS!$C$5:$C$33,B6,FICHAS!$S$5:$S$33,">=6") -> 1 | F6: =IFERROR(AVERAGEIF(FICHAS!$C$5:$C$33,B6,FICHAS!$S$5:$S$33),"") -> 4 | G6: =IFERROR(SUMPRODUCT(MAX((FICHAS!$C$5:$C$33=B6)*FICHAS!$S$5:$S$33)),"") -> 6
B7: Cliente | C7: =COUNTIF(FICHAS!$C$5:$C$33,B7) -> 4 | D7: =COUNTIFS(FICHAS!$C$5:$C$33,B7,FICHAS!$M$5:$M$33,"Alta") -> 2 | E7: =COUNTIFS(FICHAS!$C$5:$C$33,B7,FICHAS!$S$5:$S$33,">=6") -> 2 | F7: =IFERROR(AVERAGEIF(FICHAS!$C$5:$C$33,B7,FICHAS!$S$5:$S$33),"") -> 5.5 | G7: =IFERROR(SUMPRODUCT(MAX((FICHAS!$C$5:$C$33=B7)*FICHAS!$S$5:$S$33)),"") -> 9
B8: Operaciones | C8: =COUNTIF(FICHAS!$C$5:$C$33,B8) -> 2 | D8: =COUNTIFS(FICHAS!$C$5:$C$33,B8,FICHAS!$M$5:$M$33,"Alta") -> 1 | E8: =COUNTIFS(FICHAS!$C$5:$C$33,B8,FICHAS!$S$5:$S$33,">=6") -> 1 | F8: =IFERROR(AVERAGEIF(FICHAS!$C$5:$C$33,B8,FICHAS!$S$5:$S$33),"") -> 6.5 | G8: =IFERROR(SUMPRODUCT(MAX((FICHAS!$C$5:$C$33=B8)*FICHAS!$S$5:$S$33)),"") -> 9
B9: Rentabilidad | C9: =COUNTIF(FICHAS!$C$5:$C$33,B9) -> 4 | D9: =COUNTIFS(FICHAS!$C$5:$C$33,B9,FICHAS!$M$5:$M$33,"Alta") -> 3 | E9: =COUNTIFS(FICHAS!$C$5:$C$33,B9,FICHAS!$S$5:$S$33,">=6") -> 3 | F9: =IFERROR(AVERAGEIF(FICHAS!$C$5:$C$33,B9,FICHAS!$S$5:$S$33),"") -> 6.25 | G9: =IFERROR(SUMPRODUCT(MAX((FICHAS!$C$5:$C$33=B9)*FICHAS!$S$5:$S$33)),"") -> 9
B10: Tecnología | C10: =COUNTIF(FICHAS!$C$5:$C$33,B10) -> 3 | D10: =COUNTIFS(FICHAS!$C$5:$C$33,B10,FICHAS!$M$5:$M$33,"Alta") -> 2 | E10: =COUNTIFS(FICHAS!$C$5:$C$33,B10,FICHAS!$S$5:$S$33,">=6") -> 2 | F10: =IFERROR(AVERAGEIF(FICHAS!$C$5:$C$33,B10,FICHAS!$S$5:$S$33),"") -> 4.6666667 | G10: =IFERROR(SUMPRODUCT(MAX((FICHAS!$C$5:$C$33=B10)*FICHAS!$S$5:$S$33)),"") -> 6
B11: Sostenibilidad | C11: =COUNTIF(FICHAS!$C$5:$C$33,B11) -> 2 | D11: =COUNTIFS(FICHAS!$C$5:$C$33,B11,FICHAS!$M$5:$M$33,"Alta") -> 2 | E11: =COUNTIFS(FICHAS!$C$5:$C$33,B11,FICHAS!$S$5:$S$33,">=6") -> 1 | F11: =IFERROR(AVERAGEIF(FICHAS!$C$5:$C$33,B11,FICHAS!$S$5:$S$33),"") -> 6 | G11: =IFERROR(SUMPRODUCT(MAX((FICHAS!$C$5:$C$33=B11)*FICHAS!$S$5:$S$33)),"") -> 9
B12: Bebidas | C12: =COUNTIF(FICHAS!$C$5:$C$33,B12) -> 4 | D12: =COUNTIFS(FICHAS!$C$5:$C$33,B12,FICHAS!$M$5:$M$33,"Alta") -> 4 | E12: =COUNTIFS(FICHAS!$C$5:$C$33,B12,FICHAS!$S$5:$S$33,">=6") -> 3 | F12: =IFERROR(AVERAGEIF(FICHAS!$C$5:$C$33,B12,FICHAS!$S$5:$S$33),"") -> 6 | G12: =IFERROR(SUMPRODUCT(MAX((FICHAS!$C$5:$C$33=B12)*FICHAS!$S$5:$S$33)),"") -> 9
B13: Nuevos formatos | C13: =COUNTIF(FICHAS!$C$5:$C$33,B13) -> 4 | D13: =COUNTIFS(FICHAS!$C$5:$C$33,B13,FICHAS!$M$5:$M$33,"Alta") -> 3 | E13: =COUNTIFS(FICHAS!$C$5:$C$33,B13,FICHAS!$S$5:$S$33,">=6") -> 3 | F13: =IFERROR(AVERAGEIF(FICHAS!$C$5:$C$33,B13,FICHAS!$S$5:$S$33),"") -> 5 | G13: =IFERROR(SUMPRODUCT(MAX((FICHAS!$C$5:$C$33=B13)*FICHAS!$S$5:$S$33)),"") -> 6
B14: TOTAL | C14: =SUM(C5:C13) -> 29 | D14: =SUM(D5:D13) -> 21 | E14: =SUM(E5:E13) -> 19 | F14: =IFERROR(AVERAGE(FICHAS!$S$5:$S$33),"") -> 5.7241379 | G14: =MAX(FICHAS!$S$5:$S$33) -> 9
B17: Mercado (contiene) | C17: Nº tendencias
B18: BCN | C18: =COUNTIF(FICHAS!$H$5:$H$33,"*"&B18&"*") -> 15
B19: MAD | C19: =COUNTIF(FICHAS!$H$5:$H$33,"*"&B19&"*") -> 10
B20: ESP | C20: =COUNTIF(FICHAS!$H$5:$H$33,"*"&B20&"*") -> 15
B21: INT | C21: =COUNTIF(FICHAS!$H$5:$H$33,"*"&B21&"*") -> 13

Sheet PRIORIDAD
B1: TENDENCIAS POR PRIORIDAD TBNB
B2: Automatizado: ordena FICHAS por prioridad (desempate por orden de aparición).
B4: Rango | C4: ID | D4: Tendencia | E4: Área | F4: Aplicabilidad | G4: Impacto | H4: Prioridad
B5: 1 | C5: =INDEX(FICHAS!$B$5:$B$33,MATCH(LARGE(FICHAS!$X$5:$X$33,B5),FICHAS!$X$5:$X$33,0)) -> T01 | D5: =INDEX(FICHAS!$D$5:$D$33,MATCH(LARGE(FICHAS!$X$5:$X$33,B5),FICHAS!$X$5:$X$33,0)) -> Casualización de la alta cocina | E5: =INDEX(FICHAS!$C$5:$C$33,MATCH(LARGE(FICHAS!$X$5:$X$33,B5),FICHAS!$X$5:$X$33,0)) -> Concepto | F5: =INDEX(FICHAS!$M$5:$M$33,MATCH(LARGE(FICHAS!$X$5:$X$33,B5),FICHAS!$X$5:$X$33,0)) -> Alta | G5: =INDEX(FICHAS!$Q$5:$Q$33,MATCH(LARGE(FICHAS!$X$5:$X$33,B5),FICHAS!$X$5:$X$33,0)) -> 3 | H5: =INDEX(FICHAS!$S$5:$S$33,MATCH(LARGE(FICHAS!$X$5:$X$33,B5),FICHAS!$X$5:$X$33,0)) -> 9
B6: 2 | C6: =INDEX(FICHAS!$B$5:$B$33,MATCH(LARGE(FICHAS!$X$5:$X$33,B6),FICHAS!$X$5:$X$33,0)) -> T03 | D6: =INDEX(FICHAS!$D$5:$D$33,MATCH(LARGE(FICHAS!$X$5:$X$33,B6),FICHAS!$X$5:$X$33,0)) -> Cartas cortas y raciones flexibles | E6: =INDEX(FICHAS!$C$5:$C$33,MATCH(LARGE(FICHAS!$X$5:$X$33,B6),FICHAS!$X$5:$X$33,0)) -> Concepto | F6: =INDEX(FICHAS!$M$5:$M$33,MATCH(LARGE(FICHAS!$X$5:$X$33,B6),FICHAS!$X$5:$X$33,0)) -> Alta | G6: =INDEX(FICHAS!$Q$5:$Q$33,MATCH(LARGE(FICHAS!$X$5:$X$33,B6),FICHAS!$X$5:$X$33,0)) -> 3 | H6: =INDEX(FICHAS!$S$5:$S$33,MATCH(LARGE(FICHAS!$X$5:$X$33,B6),FICHAS!$X$5:$X$33,0)) -> 9
B7: 3 | C7: =INDEX(FICHAS!$B$5:$B$33,MATCH(LARGE(FICHAS!$X$5:$X$33,B7),FICHAS!$X$5:$X$33,0)) -> T07 | D7: =INDEX(FICHAS!$D$5:$D$33,MATCH(LARGE(FICHAS!$X$5:$X$33,B7),FICHAS!$X$5:$X$33,0)) -> Se come antes y se sale de día (tardeo) | E7: =INDEX(FICHAS!$C$5:$C$33,MATCH(LARGE(FICHAS!$X$5:$X$33,B7),FICHAS!$X$5:$X$33,0)) -> Cliente | F7: =INDEX(FICHAS!$M$5:$M$33,MATCH(LARGE(FICHAS!$X$5:$X$33,B7),FICHAS!$X$5:$X$33,0)) -> Alta | G7: =INDEX(FICHAS!$Q$5:$Q$33,MATCH(LARGE(FICHAS!$X$5:$X$33,B7),FICHAS!$X$5:$X$33,0)) -> 3 | H7: =INDEX(FICHAS!$S$5:$S$33,MATCH(LARGE(FICHAS!$X$5:$X$33,B7),FICHAS!$X$5:$X$33,0)) -> 9
B8: 4 | C8: =INDEX(FICHAS!$B$5:$B$33,MATCH(LARGE(FICHAS!$X$5:$X$33,B8),FICHAS!$X$5:$X$33,0)) -> T08 | D8: =INDEX(FICHAS!$D$5:$D$33,MATCH(LARGE(FICHAS!$X$5:$X$33,B8),FICHAS!$X$5:$X$33,0)) -> Cliente selectivo: sale igual, gasta con más cuidado | E8: =INDEX(FICHAS!$C$5:$C$33,MATCH(LARGE(FICHAS!$X$5:$X$33,B8),FICHAS!$X$5:$X$33,0)) -> Cliente | F8: =INDEX(FICHAS!$M$5:$M$33,MATCH(LARGE(FICHAS!$X$5:$X$33,B8),FICHAS!$X$5:$X$33,0)) -> Alta | G8: =INDEX(FICHAS!$Q$5:$Q$33,MATCH(LARGE(FICHAS!$X$5:$X$33,B8),FICHAS!$X$5:$X$33,0)) -> 3 | H8: =INDEX(FICHAS!$S$5:$S$33,MATCH(LARGE(FICHAS!$X$5:$X$33,B8),FICHAS!$X$5:$X$33,0)) -> 9
B9: 5 | C9: =INDEX(FICHAS!$B$5:$B$33,MATCH(LARGE(FICHAS!$X$5:$X$33,B9),FICHAS!$X$5:$X$33,0)) -> T11 | D9: =INDEX(FICHAS!$D$5:$D$33,MATCH(LARGE(FICHAS!$X$5:$X$33,B9),FICHAS!$X$5:$X$33,0)) -> Falta de equipos cualificados → cocinas diseñadas para la plantilla real | E9: =INDEX(FICHAS!$C$5:$C$33,MATCH(LARGE(FICHAS!$X$5:$X$33,B9),FICHAS!$X$5:$X$33,0)) -> Operaciones | F9: =INDEX(FICHAS!$M$5:$M$33,MATCH(LARGE(FICHAS!$X$5:$X$33,B9),FICHAS!$X$5:$X$33,0)) -> Alta | G9: =INDEX(FICHAS!$Q$5:$Q$33,MATCH(LARGE(FICHAS!$X$5:$X$33,B9),FICHAS!$X$5:$X$33,0)) -> 3 | H9: =INDEX(FICHAS!$S$5:$S$33,MATCH(LARGE(FICHAS!$X$5:$X$33,B9),FICHAS!$X$5:$X$33,0)) -> 9
B10: 6 | C10: =INDEX(FICHAS!$B$5:$B$33,MATCH(LARGE(FICHAS!$X$5:$X$33,B10),FICHAS!$X$5:$X$33,0)) -> T13 | D10: =INDEX(FICHAS!$D$5:$D$33,MATCH(LARGE(FICHAS!$X$5:$X$33,B10),FICHAS!$X$5:$X$33,0)) -> Costes en tensión y subidas de precio selectivas | E10: =INDEX(FICHAS!$C$5:$C$33,MATCH(LARGE(FICHAS!$X$5:$X$33,B10),FICHAS!$X$5:$X$33,0)) -> Rentabilidad | F10: =INDEX(FICHAS!$M$5:$M$33,MATCH(LARGE(FICHAS!$X$5:$X$33,B10),FICHAS!$X$5:$X$33,0)) -> Alta | G10: =INDEX(FICHAS!$Q$5:$Q$33,MATCH(LARGE(FICHAS!$X$5:$X$33,B10),FICHAS!$X$5:$X$33,0)) -> 3 | H10: =INDEX(FICHAS!$S$5:$S$33,MATCH(LARGE(FICHAS!$X$5:$X$33,B10),FICHAS!$X$5:$X$33,0)) -> 9
B11: 7 | C11: =INDEX(FICHAS!$B$5:$B$33,MATCH(LARGE(FICHAS!$X$5:$X$33,B11),FICHAS!$X$5:$X$33,0)) -> T20 | D11: =INDEX(FICHAS!$D$5:$D$33,MATCH(LARGE(FICHAS!$X$5:$X$33,B11),FICHAS!$X$5:$X$33,0)) -> Ley 1/2025 de desperdicio alimentario en vigor | E11: =INDEX(FICHAS!$C$5:$C$33,MATCH(LARGE(FICHAS!$X$5:$X$33,B11),FICHAS!$X$5:$X$33,0)) -> Sostenibilidad | F11: =INDEX(FICHAS!$M$5:$M$33,MATCH(LARGE(FICHAS!$X$5:$X$33,B11),FICHAS!$X$5:$X$33,0)) -> Alta | G11: =INDEX(FICHAS!$Q$5:$Q$33,MATCH(LARGE(FICHAS!$X$5:$X$33,B11),FICHAS!$X$5:$X$33,0)) -> 3 | H11: =INDEX(FICHAS!$S$5:$S$33,MATCH(LARGE(FICHAS!$X$5:$X$33,B11),FICHAS!$X$5:$X$33,0)) -> 9
B12: 8 | C12: =INDEX(FICHAS!$B$5:$B$33,MATCH(LARGE(FICHAS!$X$5:$X$33,B12),FICHAS!$X$5:$X$33,0)) -> T22 | D12: =INDEX(FICHAS!$D$5:$D$33,MATCH(LARGE(FICHAS!$X$5:$X$33,B12),FICHAS!$X$5:$X$33,0)) -> Sin y bajo alcohol con elaboración propia | E12: =INDEX(FICHAS!$C$5:$C$33,MATCH(LARGE(FICHAS!$X$5:$X$33,B12),FICHAS!$X$5:$X$33,0)) -> Bebidas | F12: =INDEX(FICHAS!$M$5:$M$33,MATCH(LARGE(FICHAS!$X$5:$X$33,B12),FICHAS!$X$5:$X$33,0)) -> Alta | G12: =INDEX(FICHAS!$Q$5:$Q$33,MATCH(LARGE(FICHAS!$X$5:$X$33,B12),FICHAS!$X$5:$X$33,0)) -> 3 | H12: =INDEX(FICHAS!$S$5:$S$33,MATCH(LARGE(FICHAS!$X$5:$X$33,B12),FICHAS!$X$5:$X$33,0)) -> 9
B13: 9 | C13: =INDEX(FICHAS!$B$5:$B$33,MATCH(LARGE(FICHAS!$X$5:$X$33,B13),FICHAS!$X$5:$X$33,0)) -> T02 | D13: =INDEX(FICHAS!$D$5:$D$33,MATCH(LARGE(FICHAS!$X$5:$X$33,B13),FICHAS!$X$5:$X$33,0)) -> Restaurante monoproducto o de origen | E13: =INDEX(FICHAS!$C$5:$C$33,MATCH(LARGE(FICHAS!$X$5:$X$33,B13),FICHAS!$X$5:$X$33,0)) -> Concepto | F13: =INDEX(FICHAS!$M$5:$M$33,MATCH(LARGE(FICHAS!$X$5:$X$33,B13),FICHAS!$X$5:$X$33,0)) -> Alta | G13: =INDEX(FICHAS!$Q$5:$Q$33,MATCH(LARGE(FICHAS!$X$5:$X$33,B13),FICHAS!$X$5:$X$33,0)) -> 2 | H13: =INDEX(FICHAS!$S$5:$S$33,MATCH(LARGE(FICHAS!$X$5:$X$33,B13),FICHAS!$X$5:$X$33,0)) -> 6
B14: 10 | C14: =INDEX(FICHAS!$B$5:$B$33,MATCH(LARGE(FICHAS!$X$5:$X$33,B14),FICHAS!$X$5:$X$33,0)) -> T04 | D14: =INDEX(FICHAS!$D$5:$D$33,MATCH(LARGE(FICHAS!$X$5:$X$33,B14),FICHAS!$X$5:$X$33,0)) -> Brasa y fuego vivo como eje de la cocina | E14: =INDEX(FICHAS!$C$5:$C$33,MATCH(LARGE(FICHAS!$X$5:$X$33,B14),FICHAS!$X$5:$X$33,0)) -> Producto | F14: =INDEX(FICHAS!$M$5:$M$33,MATCH(LARGE(FICHAS!$X$5:$X$33,B14),FICHAS!$X$5:$X$33,0)) -> Alta | G14: =INDEX(FICHAS!$Q$5:$Q$33,MATCH(LARGE(FICHAS!$X$5:$X$33,B14),FICHAS!$X$5:$X$33,0)) -> 2 | H14: =INDEX(FICHAS!$S$5:$S$33,MATCH(LARGE(FICHAS!$X$5:$X$33,B14),FICHAS!$X$5:$X$33,0)) -> 6
B15: 11 | C15: =INDEX(FICHAS!$B$5:$B$33,MATCH(LARGE(FICHAS!$X$5:$X$33,B15),FICHAS!$X$5:$X$33,0)) -> T14 | D15: =INDEX(FICHAS!$D$5:$D$33,MATCH(LARGE(FICHAS!$X$5:$X$33,B15),FICHAS!$X$5:$X$33,0)) -> El menú del día al límite del margen | E15: =INDEX(FICHAS!$C$5:$C$33,MATCH(LARGE(FICHAS!$X$5:$X$33,B15),FICHAS!$X$5:$X$33,0)) -> Rentabilidad | F15: =INDEX(FICHAS!$M$5:$M$33,MATCH(LARGE(FICHAS!$X$5:$X$33,B15),FICHAS!$X$5:$X$33,0)) -> Alta | G15: =INDEX(FICHAS!$Q$5:$Q$33,MATCH(LARGE(FICHAS!$X$5:$X$33,B15),FICHAS!$X$5:$X$33,0)) -> 2 | H15: =INDEX(FICHAS!$S$5:$S$33,MATCH(LARGE(FICHAS!$X$5:$X$33,B15),FICHAS!$X$5:$X$33,0)) -> 6
B16: 12 | C16: =INDEX(FICHAS!$B$5:$B$33,MATCH(LARGE(FICHAS!$X$5:$X$33,B16),FICHAS!$X$5:$X$33,0)) -> T15 | D16: =INDEX(FICHAS!$D$5:$D$33,MATCH(LARGE(FICHAS!$X$5:$X$33,B16),FICHAS!$X$5:$X$33,0)) -> Reserva con garantía y prepago contra los no-shows | E16: =INDEX(FICHAS!$C$5:$C$33,MATCH(LARGE(FICHAS!$X$5:$X$33,B16),FICHAS!$X$5:$X$33,0)) -> Rentabilidad | F16: =INDEX(FICHAS!$M$5:$M$33,MATCH(LARGE(FICHAS!$X$5:$X$33,B16),FICHAS!$X$5:$X$33,0)) -> Alta | G16: =INDEX(FICHAS!$Q$5:$Q$33,MATCH(LARGE(FICHAS!$X$5:$X$33,B16),FICHAS!$X$5:$X$33,0)) -> 2 | H16: =INDEX(FICHAS!$S$5:$S$33,MATCH(LARGE(FICHAS!$X$5:$X$33,B16),FICHAS!$X$5:$X$33,0)) -> 6
... B33: 29 | C33: =INDEX(FICHAS!$B$5:$B$33,MATCH(LARGE(FICHAS!$X$5:$X$33,B33),FICHAS!$X$5:$X$33,0)) -> T26 | D33: =INDEX(FICHAS!$D$5:$D$33,MATCH(LARGE(FICHAS!$X$5:$X$33,B33),FICHAS!$X$5:$X$33,0)) -> Food halls y mercados gastronómicos | E33: =INDEX(FICHAS!$C$5:$C$33,MATCH(LARGE(FICHAS!$X$5:$X$33,B33),FICHAS!$X$5:$X$33,0)) -> Nuevos formatos | F33: =INDEX(FICHAS!$M$5:$M$33,MATCH(LARGE(FICHAS!$X$5:$X$33,B33),FICHAS!$X$5:$X$33,0)) -> Media | G33: =INDEX(FICHAS!$Q$5:$Q$33,MATCH(LARGE(FICHAS!$X$5:$X$33,B33),FICHAS!$X$5:$X$33,0)) -> 1 | H33: =INDEX(FICHAS!$S$5:$S$33,MATCH(LARGE(FICHAS!$X$5:$X$33,B33),FICHAS!$X$5:$X$33,0)) -> 2

Sheet CASOS
B1: NEGOCIOS QUE SIRVEN DE EVIDENCIA
B2: Fuente de cada caso en la ficha de su tendencia (FICHAS, columna Fuentes).
B4: Negocio | C4: Ciudad | D4: Tendencia | E4: Qué hace | F4: Dato
B5: Bera (Martín Berasategui) | C5: Barcelona | D5: T01 | E5: Bar de tapas con barra central en el Hotel Monument; sustituye al estrella Michelin Oria | F5: ≈50 €/persona
B6: Hélène Darroze at The Connaught | C6: Londres | D6: T01 | E6: Triestrellado con carta de mediodía | F6: <135 $ frente a ≈300 $ del menú
B7: Cardinal | C7: Edimburgo | D7: T01 | E7: Estrella Michelin con 'Menú del Mercado' de 3 platos | F7: ≈34 $
B8: El Campero | C8: Madrid | D8: T02 | E8: Especialista en atún rojo de Barbate | F8: Apertura 2026
B9: Garelos | C9: Madrid | D9: T02 · T06 | E9: Cocina gallega con presentación contemporánea | F9: Apertura 2026
B10: Aleteo (Grupo Rocacho) | C10: Madrid | D10: T04 | E10: Cocina de brasas: carnes, pescados y verduras | F10: Apertura 2026
B11: Honest Greens | C11: BCN · MAD · Lisboa · Londres | D11: T04 | E11: Fast casual mediterráneo con técnicas de fuego | F11: 41 locales; Londres y París en 2026
B12: Virens / El Invernadero (Rodrigo de la Calle) | C12: Barcelona · Madrid | D12: T05 · T22 | E12: Cocina vegetal y bebidas sin alcohol fermentadas propias | F12: —
B13: Chipotle | C13: EE. UU. | D13: T05 · T10 | E13: High Protein Menu, platos 'GLP-1 friendly' | F13: Dic. 2025
B14: Obe | C14: Madrid | D14: T06 | E14: Libanés con mezze para compartir | F14: Apertura 2026
B15: Locales de tardeo de Madrid | C15: Madrid | D15: T07 | E15: 800 locales con tardeo | F15: 26,3 % de la facturación; 45 € de gasto
... B34: Turris | C34: Barcelona · Madrid | D34: T27 | E34: Cadena de panaderías | F34: Entra en Madrid en 2023

Sheet PREGUNTAS_v1.1
B1: PREGUNTAS PROPUESTAS PARA LA AUDITORÍA v1.1
B2: Salen de las tendencias. Decidir en la semana 4 cuáles entran en la herramienta.
B4: Tendencia | C4: Área de la auditoría | D4: Pregunta propuesta | E4: Coherencia | F4: Decisión TBNB | G4: Comentario
B5: T01 | C5: A01 | D5: ¿El formato (degustación, carta, barra) encaja con el ticket objetivo y con la frecuencia de visita que busca el concepto? | E5: C1 · C2
B6: T02 | C6: A04 | D6: ¿Existe plan de contingencia si falla el proveedor del producto que define el concepto (precio, temporada, cupo)? | E6: C1 · C3
B7: T03 | C7: A02 | D7: ¿La carta ofrece formatos de ración (media/entera) con precio y escandallo propios para cada formato? | E7: C2 · C3
B8: T04 | C8: A08 | D8: ¿La capacidad de la parrilla/brasa cubre el % de ventas que pasa por ella en el pico, sin depender de una sola persona? | E8: C2
B9: T05 | C9: A02 | D9: ¿La oferta vegetal y la de alto contenido proteico responden al cliente objetivo, o son platos de compromiso con baja venta? | E9: C1
B10: T06 | C10: A03 | D10: Si el concepto se presenta como 'auténtico' de un origen, ¿producto, técnica y equipo lo sostienen? | E10: C1
B11: T07 | C11: A07 | D11: ¿Turnos y mise en place están dimensionados con la curva de ventas por franja horaria real (TPV), incluida la tarde? | E11: C2 · C3
B12: T08 | C12: A01 | D12: ¿Se ha medido la relación calidad-precio percibida en reseñas (tema 'precio') y su evolución tras la última subida de carta? | E12: C1 · C3
B13: T09 | C13: A08 | D13: ¿La distribución de sala (barra, mesas de 2) se ajusta al tamaño real de grupo que muestran las reservas? | E13: C1
B14: T10 | C14: A09 | D14: ¿Las fichas técnicas recogen gramaje y coste por cada formato de ración que se vende? | E14: C1
B15: T11 | C15: A07 | D15: ¿Cuántas horas de formación necesita una nueva incorporación para ejecutar cada partida con las fichas? | E15: C2
B16: T12 | C16: A07 | D16: Si hay varios locales, ¿se ha evaluado qué elaboraciones transversales (T9) podrían centralizarse? | E16: C2 · C3
... B33: T29 | C33: A08 | D33: ¿El rediseño propuesto es compatible con la licencia y la actividad autorizada del local (humos, aforo, categoría)? | E33: C1 · C2
B35: Recuento
B36: Incluir | C36: =COUNTIF($F$5:$F$33,B36) -> 0
B37: Incluir con cambios | C37: =COUNTIF($F$5:$F$33,B37) -> 0
B38: Descartar | C38: =COUNTIF($F$5:$F$33,B38) -> 0
B39: Pendiente | C39: =COUNTIF($F$5:$F$33,B39) -> 0
B41: Nota: 4 preguntas apuntan a un área nueva de BEBIDAS, que la metodología v1.0 ya dejaba como siguiente paso (apartado 10).

Sheet FUENTES
B1: FUENTES
B2: Consultadas el 8-oct-2026. Fecha de publicación indicada en cada ficha cuando se conoce.
B4: URL | C4: Usada en
B5: https://www.timeout.es/barcelona/es/noticias/el-chef-com-mas-estrellas-michelin-de-espana-y-el-tercero-del-mundo-abre-un-restaurante-asequible-en-barcelona-042026 | C5: T01
B6: https://www.que.es/2026/07/26/martin-berasategui-cierra-estrella-michelin-tapas/ | C6: T01
B7: https://www.forbesargentina.com/lifestyle/menus-mas-cortos-precios-accesibles-formula-alta-cocina-busca-nuevos-clientes-n96944 | C7: T01
B8: https://theobjective.com/gastronomia/2026-01-09/nuevos-restaurantes-abriran-madrid-2026/ | C8: T02 · T04 · T06
B9: https://www.bolsamania.com/noticias/empresas/economia--el-66-de-los-espanoles-sale-a-bares-y-restaurantes-igual-o-mas-que-hace-un-ano-impulsado-por-los-jovenes--22469129.html | C9: T03 · T07 · T08 · T16 · T27
B10: https://hospitality-on.com/fr/restauration/vers-une-rationalisation-des-menus-et-des-process-dans-la-restauration | C10: T03
B11: https://www.elespanol.com/sociedad/20260509/espana-cambia-normas-bares-restaurantes-deberan-ofrecer-raciones-pequenas-entregar-sobras-gratis/1003744237215_0.html | C11: T03 · T20
B12: https://www.hrc.co.uk/news/hg-announces-second-london-opening-victoria-uk-expansion-gathers-pace | C12: T04
B13: https://londontheinside.com/where-have-all-the-vegans-gone/ | C13: T05
B14: https://www.axios.com/2026/01/07/restaurant-menu-high-protein-dunkin-subway-chipotle | C14: T05 · T10
B15: https://tastymondays.substack.com/p/la-invasion-coreana-llega-a-barcelona | C15: T06
... B54: https://es.ara.cat/sociedad/barcelona/ultimo-barcelona-combatir-monocultivo-turistico-comercio-ciutat-vella_1_5410794.html | C54: T29
