Workbook

Sheet Portada
A1: CASA CLEMENTINA — MODELO FINANCIERO Y VIABILIDAD
A2: The Bar N' Bar — AR03 Proyección financiera y viabilidad de negocio
A5: Fecha de construcción del modelo: 2026-10-19, con datos confirmados por el cliente en reunión de esa misma fecha.
A7: Carácter orientativo: según el SOW firmado, esta proyección se basa en hipótesis razonables a partir de la información disponible — no es una garantía de resultados.
A9: Esta versión NO sustituye las plantillas maestras ya creadas en Google Drive (Casa_Clementina_Proyección_Financiera, Casa_Clementina_P&L, Casa_Clementina_BUSINESS VIABILITY REPORT) — es el cálculo real, con fórmulas, construido en local porque el conector de edición de Google Sheets no está activo en esta sesión de trabajo. Traspasar estos números a las plantillas reales de Drive queda pendiente.
A11: Celdas en AZUL = dato de entrada (editable). Celdas en NEGRO = fórmula (no tocar a mano). Celdas en AMARILLO = hipótesis todavía sin confirmar con el cliente — pasar el ratón para ver la nota.
A13: Pestañas: Supuestos · Plan de Inversión · Personal (coste de empresa) · Costes Fijos · Punto de Equilibrio · Cuenta de Resultados Año 1 · Preguntas Abiertas

Sheet Supuestos
A1: BUSINESS ASSUMPTIONS — Supuestos del modelo
A2: Supuesto | B2: Valor | C2: Nota
A3: Aforo interior, pax (confirmado) | B3: 44 | C3: Terraza excluida: sin licencia, se excluye de toda la proyección.
A4: Días abiertos / semana | B4: 7 | C4: Confirmado por el cliente.
A5: Horario | B5: 8:00–18:00 | C5: Horario de cafetería, no de restaurante.
A6: Ticket medio — escenario bajo | B6: 11 | C6: Horquilla confirmada 11–14€.
A7: Ticket medio — escenario base | B7: 12.5 | C7: Punto medio de la horquilla.
A8: Ticket medio — escenario alto | B8: 14 | C8: Horquilla confirmada 11–14€.
A9: Estacionalidad jul-ago (caída sobre el resto del año) | B9: -0.6 | C9: Confirmado: -60% en julio y agosto.
A10: COGS % sobre ventas (food cost corriente) | B10: 0.3 | C10: PENDIENTE DE CONFIRMAR con el cliente — valor de referencia de cafetería/bar, no dato real.
A11: IRPF estimado (para pasar neto a bruto) | B11: 0.15 | C11: Aproximación para el cálculo de coste de empresa — depende de la situación personal real de cada contrato; validar con gestoría antes de cerrar el informe.
A12: Seguridad Social a cargo de la empresa | B12: 0.33 | C12: Dato dado por Andrea en la reunión.
A13: IVA hostelería (tipo reducido) | B13: 0.1 | C13: Tipo legal vigente para servicios de hostelería en España.

Sheet Plan de Inversión
A1: INVESTMENT PLAN — Plan de inversión
A3: Ya invertido (referencia — no es necesidad de capital nuevo)
A4: Importe total pagado a día de hoy (obra + fianza + alquileres + licencias + arquitectos + máquina de café, etc. — incluye el proyecto acústico de Absotec, confirmado por el cliente como ya incluido en la obra) | B4: 240000
A6: Pendiente de lo ya valorado y presupuestado dentro de la obra
A7: Resto de la maquinaria de cocina/barra (saldo pendiente) | B7: 8000
A9: Partidas nuevas para abrir (pago único, fuera del presupuesto de obra ya cerrado)
A10: Mobiliario (mesas, sillas, bancos) | B10: 15000
A11: Pequeños electrodomésticos | B11: 3500
A12: Food cost inicial (stock de apertura) | B12: 5000
A13: Alquiler de octubre | B13: 1800
A14: TPV (hardware) — Aproximado — confirmar contra presupuesto real de Square. | B14: 300
A15: Software (instalación/licencia inicial) — PENDIENTE: Andrea dará la cifra cuando se le pida — no inventar un número. | B15: 0
A17: TOTAL inversión pendiente para abrir (valorado + nuevas partidas) | B17: =SUM(B7:B7)+SUM(B10:B15) -> 33600
A19: Nota: 2.600€ de los pendientes son un reembolso interno de la SL a Fuensanta (adelantó de su bolsillo), no una necesidad de capital externo nuevo — inclúyelo en el total de obligaciones de la SL, pero no lo confundas con inversión a buscar fuera.

Sheet Personal
A1: COST STRUCTURE — Personal: coste de empresa
A2: Fórmula: Bruto = Neto / (1 − IRPF estimado) · Coste de empresa = Bruto × (1 + SS empresa). IRPF y SS vienen de la pestaña Supuestos.
A3: Puesto | B3: Nº personas (PENDIENTE turnos) | C3: Neto/mes | D3: Bruto/mes | E3: Coste empresa/mes (1 persona) | F3: Coste empresa/mes (total puesto) | G3: Coste empresa/año (total puesto)
A4: Manager | B4: 1 | C4: 1800 | D4: =C4/(1-Supuestos!$B$11) -> 2117.6471 | E4: =D4*(1+Supuestos!$B$12) -> 2816.4706 | F4: =E4*B4 -> 2816.4706 | G4: =F4*12 -> 33797.647
A5: Barista | B5: 1 | C5: 1500 | D5: =C5/(1-Supuestos!$B$11) -> 1764.7059 | E5: =D5*(1+Supuestos!$B$12) -> 2347.0588 | F5: =E5*B5 -> 2347.0588 | G5: =F5*12 -> 28164.706
A6: Camarero/a | B6: 2 | C6: 1400 | D6: =C6/(1-Supuestos!$B$11) -> 1647.0588 | E6: =D6*(1+Supuestos!$B$12) -> 2190.5882 | F6: =E6*B6 -> 4381.1765 | G6: =F6*12 -> 52574.118
A7: Ayudante de camarero/a | B7: 1 | C7: 1400 | D7: =C7/(1-Supuestos!$B$11) -> 1647.0588 | E7: =D7*(1+Supuestos!$B$12) -> 2190.5882 | F7: =E7*B7 -> 2190.5882 | G7: =F7*12 -> 26287.059
A8: Cocinero/a | B8: 1 | C8: 1400 | D8: =C8/(1-Supuestos!$B$11) -> 1647.0588 | E8: =D8*(1+Supuestos!$B$12) -> 2190.5882 | F8: =E8*B8 -> 2190.5882 | G8: =F8*12 -> 26287.059
A9: Ayudante de cocina | B9: 1 | C9: 1400 | D9: =C9/(1-Supuestos!$B$11) -> 1647.0588 | E9: =D9*(1+Supuestos!$B$12) -> 2190.5882 | F9: =E9*B9 -> 2190.5882 | G9: =F9*12 -> 26287.059
A10: Jefe/a de cocina | B10: 1 | C10: 1600 | D10: =C10/(1-Supuestos!$B$11) -> 1882.3529 | E10: =D10*(1+Supuestos!$B$12) -> 2503.5294 | F10: =E10*B10 -> 2503.5294 | G10: =F10*12 -> 30042.353
A11: TOTAL personal | B11: =SUM(B4:B10) -> 8 | F11: =SUM(F4:F10) -> 18620 | G11: =SUM(G4:G10) -> 223440

Sheet Costes Fijos
A1: COST STRUCTURE — Costes fijos mensuales (sin personal)
A2: Concepto | B2: Importe/mes | C2: Nota
A3: Alquiler (año 1-2) | B3: 1800
A4: Alarma | B4: 50 | C4: Reclasificado hoy: cuota mensual, no pago único.
A5: Wifi | B5: 50 | C5: Reclasificado hoy: cuota mensual, no pago único.
A6: Software TPV | B6: 80 | C6: Aproximado — confirmar contra presupuesto real de Square.
A7: Suministros (luz/agua/gas) | B7: 0 | C7: PENDIENTE: no hay dato real todavía — no inventar.
A8: Seguro del local | B8: 0 | C8: PENDIENTE: no hay dato real todavía — no inventar.
A9: TOTAL costes fijos (sin personal) | B9: =SUM(B3:B8) -> 1980
A11: TOTAL costes fijos + personal | B11: =B9+Personal!F11 -> 20600
A13: Nota sobre renta escalonada: a partir del año 3 el alquiler sube (1.900€ → 2.000€ → 2.100€ → 2.100€+IPC) — esta pestaña usa el alquiler de los años 1-2; ajustar manualmente la celda B3 al construir la proyección de los años siguientes.

Sheet Punto de Equilibrio
A1: VIABILITY ANALYSIS — Punto de equilibrio
A3: Costes fijos totales mensuales (incl. personal) | B3: ='Costes Fijos'!B11 -> 20600
A4: COGS % sobre ventas | B4: =Supuestos!B10 -> 0.3
A5: Margen de contribución % (1 − COGS%) | B5: =1-B4 -> 0.7
A6: Ventas mensuales necesarias para cubrir costes (punto de equilibrio) | B6: =B3/B5 -> 29428.571
A8: Visitas/día necesarias para llegar al punto de equilibrio, según ticket medio (mes de 30,4 días)
A9: Escenario ticket medio | B9: Ticket medio | C9: Visitas/día necesarias | D9: Capacidad teórica/día (44 pax × turnos razonables)
A10: Bajo | B10: =Supuestos!B6 -> 11 | C10: =(B6/30.4)/B10 -> 88.004101 | D10: =Supuestos!$B$3*3 -> 132
A11: Base | B11: =Supuestos!B7 -> 12.5 | C11: =(B6/30.4)/B11 -> 77.443609 | D11: =Supuestos!$B$3*3 -> 132
A12: Alto | B12: =Supuestos!B8 -> 14 | C12: =(B6/30.4)/B12 -> 69.146079 | D12: =Supuestos!$B$3*3 -> 132
A14: Lectura: la capacidad teórica asume 3 turnos completos de aforo al día (44 pax × 3) como referencia de contexto, no como dato confirmado por el cliente — compárese con las visitas/día necesarias para ver si el punto de equilibrio es realista dentro del horario de 8:00-18:00h.

Sheet Cuenta Resultados Año 1
A1: FINANCIAL PROJECTIONS — Cuenta de Resultados, Año 1 (mensual)
A2: Visitas/día (fila 4) parte del propio punto de equilibrio como marcador neutro — SUSTITUIR por la cifra real de visitas/día esperadas en cuanto el cliente/Andrea la confirme. Mientras no se actualice, esta cuenta de resultados muestra 'cubre gastos, no gana ni pierde', no una proyección real.
A3: Concepto | B3: Noviembre | C3: Diciembre | D3: Enero | E3: Febrero | F3: Marzo | G3: Abril | H3: Mayo | I3: Junio | J3: Julio | K3: Agosto | L3: Septiembre | M3: Octubre | N3: TOTAL AÑO
A4: Factor estacional (1 = normal, Supuestos!B9 en jul/ago) | B4: 1 | C4: 1 | D4: 1 | E4: 1 | F4: 1 | G4: 1 | H4: 1 | I4: 1 | J4: =1+Supuestos!$B$9 -> 0.4 | K4: =1+Supuestos!$B$9 -> 0.4 | L4: 1 | M4: 1
A5: Ticket medio aplicado | B5: =Supuestos!$B$7 -> 12.5 | C5: =Supuestos!$B$7 -> 12.5 | D5: =Supuestos!$B$7 -> 12.5 | E5: =Supuestos!$B$7 -> 12.5 | F5: =Supuestos!$B$7 -> 12.5 | G5: =Supuestos!$B$7 -> 12.5 | H5: =Supuestos!$B$7 -> 12.5 | I5: =Supuestos!$B$7 -> 12.5 | ... M5: =Supuestos!$B$7 -> 12.5
A6: Visitas/día (PENDIENTE DE CONFIRMAR — ver nota arriba) | B6: ='Punto de Equilibrio'!$C$11*B4 -> 77.443609 | C6: ='Punto de Equilibrio'!$C$11*C4 -> 77.443609 | D6: ='Punto de Equilibrio'!$C$11*D4 -> 77.443609 | E6: ='Punto de Equilibrio'!$C$11*E4 -> 77.443609 | F6: ='Punto de Equilibrio'!$C$11*F4 -> 77.443609 | G6: ='Punto de Equilibrio'!$C$11*G4 -> 77.443609 | H6: ='Punto de Equilibrio'!$C$11*H4 -> 77.443609 | I6: ='Punto de Equilibrio'!$C$11*I4 -> 77.443609 | ... M6: ='Punto de Equilibrio'!$C$11*M4 -> 77.443609
A7: Ingresos | B7: =B6*30.4*B5 -> 29428.571 | C7: =C6*30.4*C5 -> 29428.571 | D7: =D6*30.4*D5 -> 29428.571 | E7: =E6*30.4*E5 -> 29428.571 | F7: =F6*30.4*F5 -> 29428.571 | G7: =G6*30.4*G5 -> 29428.571 | H7: =H6*30.4*H5 -> 29428.571 | I7: =I6*30.4*I5 -> 29428.571 | ... M7: =M6*30.4*M5 -> 29428.571 | N7: =SUM(B7:M7) -> 317828.57
A8: COGS (food cost corriente) | B8: =-B7*Supuestos!$B$10 -> -8828.5714 | C8: =-C7*Supuestos!$B$10 -> -8828.5714 | D8: =-D7*Supuestos!$B$10 -> -8828.5714 | E8: =-E7*Supuestos!$B$10 -> -8828.5714 | F8: =-F7*Supuestos!$B$10 -> -8828.5714 | G8: =-G7*Supuestos!$B$10 -> -8828.5714 | H8: =-H7*Supuestos!$B$10 -> -8828.5714 | I8: =-I7*Supuestos!$B$10 -> -8828.5714 | ... M8: =-M7*Supuestos!$B$10 -> -8828.5714 | N8: =SUM(B8:M8) -> -95348.571
A9: Margen bruto | B9: =B7+B8 -> 20600 | C9: =C7+C8 -> 20600 | D9: =D7+D8 -> 20600 | E9: =E7+E8 -> 20600 | F9: =F7+F8 -> 20600 | G9: =G7+G8 -> 20600 | H9: =H7+H8 -> 20600 | I9: =I7+I8 -> 20600 | ... M9: =M7+M8 -> 20600 | N9: =SUM(B9:M9) -> 222480
A10: Coste de personal (coste de empresa) | B10: =-Personal!$F$11 -> -18620 | C10: =-Personal!$F$11 -> -18620 | D10: =-Personal!$F$11 -> -18620 | E10: =-Personal!$F$11 -> -18620 | F10: =-Personal!$F$11 -> -18620 | G10: =-Personal!$F$11 -> -18620 | H10: =-Personal!$F$11 -> -18620 | I10: =-Personal!$F$11 -> -18620 | ... M10: =-Personal!$F$11 -> -18620 | N10: =SUM(B10:M10) -> -223440
A11: Costes fijos (sin personal) | B11: =-'Costes Fijos'!$B$9 -> -1980 | C11: =-'Costes Fijos'!$B$9 -> -1980 | D11: =-'Costes Fijos'!$B$9 -> -1980 | E11: =-'Costes Fijos'!$B$9 -> -1980 | F11: =-'Costes Fijos'!$B$9 -> -1980 | G11: =-'Costes Fijos'!$B$9 -> -1980 | H11: =-'Costes Fijos'!$B$9 -> -1980 | I11: =-'Costes Fijos'!$B$9 -> -1980 | ... M11: =-'Costes Fijos'!$B$9 -> -1980 | N11: =SUM(B11:M11) -> -23760
A12: EBITDA | B12: =B9+B10+B11 -> 7.2759576e-12 | C12: =C9+C10+C11 -> 7.2759576e-12 | D12: =D9+D10+D11 -> 7.2759576e-12 | E12: =E9+E10+E11 -> 7.2759576e-12 | F12: =F9+F10+F11 -> 7.2759576e-12 | G12: =G9+G10+G11 -> 7.2759576e-12 | H12: =H9+H10+H11 -> 7.2759576e-12 | I12: =I9+I10+I11 -> 7.2759576e-12 | ... M12: =M9+M10+M11 -> 7.2759576e-12 | N12: =SUM(B12:M12) -> -24720
A13: Margen EBITDA % | B13: =IFERROR(B12/B7,0) -> 2.4724128e-16 | C13: =IFERROR(C12/C7,0) -> 2.4724128e-16 | D13: =IFERROR(D12/D7,0) -> 2.4724128e-16 | E13: =IFERROR(E12/E7,0) -> 2.4724128e-16 | F13: =IFERROR(F12/F7,0) -> 2.4724128e-16 | G13: =IFERROR(G12/G7,0) -> 2.4724128e-16 | H13: =IFERROR(H12/H7,0) -> 2.4724128e-16 | I13: =IFERROR(I12/I7,0) -> 2.4724128e-16 | ... M13: =IFERROR(M12/M7,0) -> 2.4724128e-16

Sheet Preguntas Abiertas
A1: PREGUNTAS ABIERTAS ANTES DE CERRAR EL INFORME
A3: 1. Visitas/día o facturación objetivo esperada — sin este dato, la Cuenta de Resultados usa el propio punto de equilibrio como marcador neutro (ni gana ni pierde). Es el dato que más cambia el resultado real.
A4: 2. Headcount real por puesto, según el plan de turnos (8h/día, 7 días, ajustado a necesidad) — la pestaña Personal usa un headcount de ejemplo (8 personas en total) marcado en amarillo.
A5: 3. Coste real del software (instalación/licencia inicial) — Andrea lo dará cuando se le pida.
A6: 4. Presupuesto real de Square (TPV + software mensual) — las cifras de hoy (300€ + 80€/mes) son aproximadas.
A7: 5. COGS % real sobre ventas corrientes — se ha usado 30% como referencia de cafetería/bar, no un dato del cliente.
A8: 6. Suministros (luz/agua/gas) y seguro del local — no hay dato real todavía, no se han incluido en costes fijos.
A9: 7. IRPF real aplicable a cada contrato — se ha usado 15% como aproximación para calcular el coste de empresa; validar con gestoría antes de dar el informe por definitivo.
A10: 8. ¿"Final de obra: 15.000€" de la lista de pendientes antigua es saldo de KIPER o partida aparte? (pregunta ya identificada, sigue sin respuesta explícita en los datos de hoy).
A11: 9. Traspaso / Panadario y pacto de socios — siguen pendientes de la propia reunión con el cliente, según el gap analysis original.
